QElephant/Circuit.py
QElephant/Matrix.py
QElephant/QuBit.py
QElephant/__init__.py
QElephant-1.0.10.dist-info/METADATA
QElephant-1.0.10.dist-info/WHEEL
QElephant-1.0.10.dist-info/top_level.txt
QElephant-1.0.10.dist-info/RECORD
