Metadata-Version: 2.1
Name: QElephant
Version: 1.0.10
Summary: A small python module simulating a quantum computer
Author: Didictateur
Author-email: decosse.adrien@gmail.com
